[
  { "title": "Barcelona", "date": "12.05. - 20.05.20" },
  { "title": "Berlin Messe ITB", "date": "07.03. - 10.03.20" },
  { "title": "Roadtrip New York - Miami", "date": "19.07. - 06.08.20" },
  {
    "title": "Mallorca mit Vivien, Saskia & Sarah",
    "date": "12.05. - 20.05.20"
  },
  { "title": "Osterurlaub Kanaren", "date": "12.05. - 20.05.20" },
  { "title": "Griechenland - Kreta", "date": "23.11. - 28.11.19" },
  { "title": "Gran Canaria, Kanaren/Spanien", "date": "12.05. - 20.05.20" },
  { "title": "Amsterdam Wochenendtrip", "date": "Herbst 2019" },
  { "title": "Basel", "date": "März 2019 - Fasnacht" },
  { "title": "Thailand - Koh Samui", "date": "Juli / 2017" }
]
